LICENSE
README.md
setup.py
fusionaskatest/__init__.py
fusionaskatest/github_api.py
fusionaskatest.egg-info/PKG-INFO
fusionaskatest.egg-info/SOURCES.txt
fusionaskatest.egg-info/dependency_links.txt
fusionaskatest.egg-info/not-zip-safe
fusionaskatest.egg-info/requires.txt
fusionaskatest.egg-info/top_level.txt