Metadata-Version: 2.1
Name: fusionaskatest
Version: 0.1
Summary: testando instalações
Home-page: https://github.com/AskaVictoria/fusion
Author: Aska Victoria
Author-email: aska.pereira@gmail.com
License:                     GNU AFFERO GENERAL PUBLIC LICENSE
Platform: UNKNOWN
Classifier: Development Status :: 2 - Pre-Alpha
Classifier: Environment :: Web Environment
Classifier: Intended Audience :: Developers
Classifier: License :: OSI Approved :: BSD License
Classifier: Operating System :: OS Independent
Classifier: Programming Language :: Python
Classifier: Framework :: Pytest
License-File: LICENSE
